web3_calculator_usage/__init__.py
web3_calculator_usage-0.0.1.dist-info/LICENSE
web3_calculator_usage-0.0.1.dist-info/METADATA
web3_calculator_usage-0.0.1.dist-info/WHEEL
web3_calculator_usage-0.0.1.dist-info/top_level.txt
web3_calculator_usage-0.0.1.dist-info/RECORD
