Metadata-Version: 2.1
Name: web3-calculator-usage
Version: 0.0.1
Summary: A simple web3 calculator package usage
Home-page: https://github.com/Zcb991/web3-calculator
Author: Zcb991
Author-email: 2952964392@qq.com
Classifier: Programming Language :: Python :: 3
Classifier: License :: OSI Approved :: MIT License
Classifier: Operating System :: OS Independent
License-File: LICENSE
Requires-Dist: web3-calculator
Requires-Dist: requests
